omegaup_hook_tools/__init__.py
omegaup_hook_tools/__main__.py
omegaup_hook_tools/_version.py
omegaup_hook_tools/git_tools.py
omegaup_hook_tools/lint.py
omegaup_hook_tools/linters.py
omegaup_hook_tools/py.typed
omegaup_hook_tools/data/tidy
omegaup_hook_tools/data/tidy.txt
omegaup_hook_tools/data/phpcbf/Standards/OmegaUp/ruleset.xml
omegaup_hook_tools/data/phpcbf/Standards/OmegaUp/Sniffs/Classes/ClassDeclarationSniff.php
omegaup_hook_tools/data/phpcbf/Standards/OmegaUp/Sniffs/Formatting/CastSniff.php
omegaup_hook_tools/data/phpcbf/Standards/OmegaUp/Sniffs/Formatting/NullComparisonSniff.php
omegaup_hook_tools/data/phpcbf/Standards/OmegaUp/Sniffs/Functions/MultiLineFunctionDeclarationSniff.php
omegaup_hook_tools/data/phpcbf/Standards/OmegaUp/Sniffs/Methods/FunctionCallSignatureSniff.php
omegaup_hook_tools-1.0.9.dist-info/LICENSE
omegaup_hook_tools-1.0.9.dist-info/METADATA
omegaup_hook_tools-1.0.9.dist-info/WHEEL
omegaup_hook_tools-1.0.9.dist-info/top_level.txt
omegaup_hook_tools-1.0.9.dist-info/RECORD
