Metadata-Version: 2.1
Name: omegaup-hook-tools
Version: 1.0.9
Summary: Utilities for writing git hooks
Author-email: omegaUp <lhchavez@omegaup.org>
Project-URL: Homepage, https://github.com/omegaup/libomegaup
Project-URL: Bug Tracker, https://github.com/omegaup/libomegaup/issues
Classifier: Programming Language :: Python :: 3
Classifier: License :: OSI Approved :: BSD License
Classifier: Operating System :: OS Independent
Requires-Python: >=3.6
License-File: LICENSE
Requires-Dist: mypy (==0.991)
Requires-Dist: pycodestyle (==2.9.1)
Requires-Dist: pylint (==2.15.6)
Provides-Extra: testing
Requires-Dist: pytest (>=7.1) ; extra == 'testing'
